configurations/__init__.py
configurations/config.py
configurations/template_editor_config.py
numimage/__init__.py
numimage/color_picker.py
numimage/geometry.py
numimage/getsvgrect.py
numimage/math_h.py
numimage/outline.py
numimage/potrace.py
numimage/proc_bbox.py
numimage/proc_color.py
numimage/proc_image.py
numimage/proc_points.py
numimage/reverse_logo.py
string_h/__init__.py
string_h/reverse.py
numimage-0.0.4.dist-info/LICENSE.txt
numimage-0.0.4.dist-info/METADATA
numimage-0.0.4.dist-info/WHEEL
numimage-0.0.4.dist-info/top_level.txt
numimage-0.0.4.dist-info/RECORD
