Metadata-Version: 2.1
Name: numimage
Version: 0.0.4
Summary: 验证打包功能的测试包, 请勿下载
Home-page: https://github.com/JackyFuHk/numimage
Author: JackyFu
Author-email: 343651570@qq.com
License: MIT
Keywords: jacky package demo
Classifier: Development Status :: 3 - Alpha
Classifier: Intended Audience :: Developers
Classifier: Topic :: Software Development :: Build Tools
Classifier: License :: OSI Approved :: MIT License
Classifier: Programming Language :: Python :: 3
Classifier: Programming Language :: Python :: 3.2
Classifier: Programming Language :: Python :: 3.3
Classifier: Programming Language :: Python :: 3.4
Classifier: Operating System :: OS Independent
Requires-Python: >=3.6
License-File: LICENSE.txt
Requires-Dist: pytest
Requires-Dist: torch (==2.0.1)
Requires-Dist: torchvision
Requires-Dist: svg.path
